vs301_util/__init__.py
vs301_util/alsamixer.py
vs301_util/usb_eth_finder.py
vs301_util-0.1.2.dist-info/LICENSE
vs301_util-0.1.2.dist-info/METADATA
vs301_util-0.1.2.dist-info/WHEEL
vs301_util-0.1.2.dist-info/top_level.txt
vs301_util-0.1.2.dist-info/RECORD
